submission_validator/__init__.py
submission_validator/services/__init__.py
submission_validator/services/ena_taxonomy.py
submission_validator/validation/__init__.py
submission_validator/validation/docker.py
submission_validator/validation/json.py
submission_validator/validation/taxonomy.py
submission_validator/validation/upload.py
submission_validator/validation/schema/__init__.py
submission_validator-0.1.2.dist-info/LICENSE
submission_validator-0.1.2.dist-info/METADATA
submission_validator-0.1.2.dist-info/WHEEL
submission_validator-0.1.2.dist-info/top_level.txt
submission_validator-0.1.2.dist-info/RECORD
