Metadata-Version: 2.1
Name: submission-validator
Version: 0.1.2
Summary: A Python library that contains validation methods for submissions that goes into EBI archives.
Home-page: https://github.com/ebi-ait/submission-validator
License: UNKNOWN
Platform: UNKNOWN
Classifier: Development Status :: 3 - Alpha
Classifier: Programming Language :: Python :: 3
Classifier: Operating System :: OS Independent
Requires-Dist: requests
Requires-Dist: docker
Requires-Dist: submission-broker
Requires-Dist: boto3
Requires-Dist: lxml
